wrecked/__init__.py
wrecked-1.0.10.data/data/lib/libwrecked.so
wrecked-1.0.10.dist-info/LICENSE
wrecked-1.0.10.dist-info/METADATA
wrecked-1.0.10.dist-info/WHEEL
wrecked-1.0.10.dist-info/top_level.txt
wrecked-1.0.10.dist-info/RECORD
