Metadata-Version: 2.1
Name: wrecked
Version: 1.0.10
Summary: Bindings for the wrecked terminal graphics library
Home-page: https://github.com/quintinfsmith/wrecked_bindings
Author: Quintin Smith
Author-email: smith.quintin@protonmail.com
License: UNKNOWN
Platform: UNKNOWN
Classifier: Programming Language :: Python :: 3
Classifier: Programming Language :: Rust
Classifier: License :: OSI Approved :: GNU Lesser General Public License v2 or later (LGPLv2+)
Classifier: Operating System :: POSIX :: Linux
Requires-Python: >=3.6
Requires-Dist: cffi
